slipper/__init__.py
slipper/_version.py
slipper/fourier_methods.py
slipper/logger.py
slipper/example_datasets/__init__.py
slipper/example_datasets/ar_data.py
slipper/example_datasets/lisa_data.py
slipper/plotting/__init__.py
slipper/plotting/gif_creator.py
slipper/plotting/plot_sampling_metadata.py
slipper/plotting/plot_spline_model_and_data.py
slipper/plotting/style.mplstyle
slipper/plotting/utils.py
slipper/sample/__init__.py
slipper/sample/base_sampler.py
slipper/sample/post_processing.py
slipper/sample/sampling_result.py
slipper/sample/utils.py
slipper/sample/log_pspline_sampler/__init__.py
slipper/sample/log_pspline_sampler/bayesian_functions.py
slipper/sample/log_pspline_sampler/log_pspline_sampler.py
slipper/sample/pspline_sampler/__init__.py
slipper/sample/pspline_sampler/bayesian_functions.py
slipper/sample/pspline_sampler/pspline_sampler.py
slipper/splines/__init__.py
slipper/splines/init_optimization.py
slipper/splines/p_splines.py
slipper/splines/utils.py
slipper/splines/knot_locator/__init__.py
slipper/splines/knot_locator/methods.py
pyslipper-0.0.2.dist-info/METADATA
pyslipper-0.0.2.dist-info/WHEEL
pyslipper-0.0.2.dist-info/top_level.txt
pyslipper-0.0.2.dist-info/RECORD
