Metadata-Version: 2.1
Name: pyslipper
Version: 0.0.2
Summary: Fit your data with P-Splines!
Author-email: Patricio M Russel <patricio_email_here@gmail.com>, Avi Vajpeyi <avi.vajpeyi@gmail.com>, "Nazeela A." <nazeela_email_here@gmail.com>
Project-URL: Homepage, https://github.com/avivajpeyi/pyslipper
Project-URL: Bug Reports, https://github.com/avivajpeyi/pyslipper/issues
Project-URL: Funding, https://donate.pypi.org
Project-URL: Say Thanks!, http://saythanks.io/to/example
Project-URL: Source, https://github.com/avivajpeyi/pyslipper/
Classifier: Development Status :: 3 - Alpha
Classifier: Intended Audience :: Science/Research
Classifier: License :: OSI Approved :: MIT License
Classifier: Operating System :: OS Independent
Classifier: Programming Language :: Python :: 3.8
Requires-Python: >=3.8
Requires-Dist: arviz
Requires-Dist: spectral
Requires-Dist: scikit-fda
Requires-Dist: matplotlib
Requires-Dist: imageio
Requires-Dist: pygifsicle
Requires-Dist: bilby
Requires-Dist: statsmodels
Requires-Dist: loguru
Provides-Extra: dev
Requires-Dist: pytest >=6.0 ; extra == 'dev'
Requires-Dist: pytest-cov >=4.1.0 ; extra == 'dev'
Requires-Dist: pre-commit ; extra == 'dev'
Requires-Dist: flake8 >=5.0.4 ; extra == 'dev'
Requires-Dist: black >=22.12.0 ; extra == 'dev'
Requires-Dist: jupyter-book ; extra == 'dev'
